cdk_mate/__init__.py
cdk_mate/_version.py
cdk_mate/api.py
cdk_mate/cli/__init__.py
cdk_mate/cli/api.py
cdk_mate/cli/cli_cmd.py
cdk_mate/cli/cli_utils.py
cdk_mate/docs/__init__.py
cdk_mate/paths.py
cdk_mate/stack_ctx.py
cdk_mate/tests/__init__.py
cdk_mate/tests/bsm_enum.py
cdk_mate/tests/helper.py
cdk_mate/tests/mock_aws.py
cdk_mate/tests/runtime.py
cdk_mate/tests/stack_ctx_enum.py
cdk_mate/tests/stack_enum.py
cdk_mate/tests/stacks/__init__.py
cdk_mate/tests/stacks/stack1/__init__.py
cdk_mate/tests/stacks/stack1/iac_define.py
cdk_mate/tests/stacks/stack1/iac_define_01_everything.py
cdk_mate/tests/stacks/stack2/__init__.py
cdk_mate/tests/stacks/stack2/iac_define.py
cdk_mate/tests/stacks/stack2/iac_define_01_everything.py
cdk_mate/utils.py
cdk_mate/vendor/__init__.py
cdk_mate/vendor/better_pathlib.py
cdk_mate/vendor/pytest_cov_helper.py
cdk_mate-0.1.6.dist-info/AUTHORS.rst
cdk_mate-0.1.6.dist-info/LICENSE.txt
cdk_mate-0.1.6.dist-info/METADATA
cdk_mate-0.1.6.dist-info/WHEEL
cdk_mate-0.1.6.dist-info/RECORD
